{
  "users": [
    {
      "id": "1",
      "username": "username",
      "name": "Name",
      "email": "name@email.com",
      "passwordHash": "password",
      "registrationDate": "2020-01-01",
      "lastLogin": "2020-01-01",
      "isAdmin": true,
      "tags": [
        "1"
      ],
      "stories": [
        "1"
      ],
      "comments": [
        "1"
      ]
    }
  ],
  "stories": [
    {
      "id": "1",
      "authorId": "1",
      "title": "Story title",
      "imageUrl": "https://image.com/image.jpg",
      "createdAt": "2020-01-01",
      "updatedAt": "2020-01-01",
      "description": "Story description",
      "content": "Story content",
      "likes": 100,
      "views": 100,
      "comments": [
        "1"
      ]
    }
  ],
  "comments": [
    {
      "id": "1",
      "authorId": "1",
      "postId": "1",
      "content": "a comment about post 1",
      "likes": 100,
      "createdAt": "2020-01-01"
    }
  ],
  "topics": [
    {
      "id": "1",
      "name": "tag1",
      "stories": [
        "1"
      ]
    }
  ]
}